beetsplug/lyricsmanager.py
beets_lyrics_manager-0.0.3.dist-info/METADATA
beets_lyrics_manager-0.0.3.dist-info/WHEEL
beets_lyrics_manager-0.0.3.dist-info/top_level.txt
beets_lyrics_manager-0.0.3.dist-info/RECORD
